Obstacle_Detection/Obstacle_Detection.py
Obstacle_Detection/__init__.py
Obstacle_Detection/utils.py
voxel_object_detection/Obstacle_Detection.py
voxel_object_detection/__init__.py
voxel_object_detection/detection.py
voxel_object_detection/utils.py
voxel_obstacle_detection-0.1.0.dist-info/LICENCE
voxel_obstacle_detection-0.1.0.dist-info/METADATA
voxel_obstacle_detection-0.1.0.dist-info/WHEEL
voxel_obstacle_detection-0.1.0.dist-info/top_level.txt
voxel_obstacle_detection-0.1.0.dist-info/RECORD
