Metadata-Version: 2.1
Name: voxel-obstacle-detection
Version: 0.1.0
Summary: A Python package for obstacle detection in voxel maps using Open3D and raycasting
Home-page: https://github.com/alexandre-dc/voxel-object-detection
Author: Alexandre Correia
Author-email: alexandre17dc@gmail.com
License: MIT
Platform: UNKNOWN
Classifier: Programming Language :: Python :: 3
Classifier: License :: OSI Approved :: MIT License
Classifier: Operating System :: OS Independent
Requires-Python: >=3.9
License-File: LICENCE
Requires-Dist: numpy<2.0.0
Requires-Dist: open3d>=0.18.0
Requires-Dist: scikit-learn
